package_rling/DataCleaning.py
package_rling/DataEngineering.py
package_rling/DataTransformation.py
package_rling/FeatureSelection.py
package_rling/MachineLearningModel.py
package_rling/Normalization.py
package_rling/__init__.py
package_rling-0.1.3.dist-info/WHEEL
package_rling-0.1.3.dist-info/METADATA
package_rling-0.1.3.dist-info/RECORD
